LICENSE
nubia/__init__.py
nubia/internal/__init__.py
nubia/internal/blackcmd.py
nubia/internal/cmdbase.py
nubia/internal/cmdloader.py
nubia/internal/commands/__init__.py
nubia/internal/commands/builtin.py
nubia/internal/commands/help.py
nubia/internal/completion.py
nubia/internal/constants.py
nubia/internal/context.py
nubia/internal/deprecation.py
nubia/internal/exceptions.py
nubia/internal/helpers.py
nubia/internal/interactive.py
nubia/internal/io/__init__.py
nubia/internal/io/eventbus.py
nubia/internal/io/logger.py
nubia/internal/io/session_logger.py
nubia/internal/ipython.py
nubia/internal/nubia.py
nubia/internal/options.py
nubia/internal/parser.py
nubia/internal/plugin_interface.py
nubia/internal/registry.py
nubia/internal/registry_tools.py
nubia/internal/typing/__init__.py
nubia/internal/typing/argparse.py
nubia/internal/typing/builder.py
nubia/internal/typing/inspect.py
nubia/internal/ui/__init__.py
nubia/internal/ui/ipython.py
nubia/internal/ui/lexer.py
nubia/internal/ui/statusbar.py
nubia/internal/ui/style.py
nubia/internal/usage_logger_interface.py
nubia_cli-0.2.10.dist-info/LICENSE
nubia_cli-0.2.10.dist-info/METADATA
nubia_cli-0.2.10.dist-info/WHEEL
nubia_cli-0.2.10.dist-info/RECORD
