Metadata-Version: 2.1
Name: nubia-cli
Version: 0.2.10
Summary: A fork of Meta's nubia, a framework for building beautiful shells.
License: BSD
Author: Ahmed Soliman
Author-email: asoli@fb.com
Requires-Python: >=3.8.1,<3.12
Classifier: License :: Other/Proprietary License
Classifier: Programming Language :: Python :: 3
Classifier: Programming Language :: Python :: 3.9
Classifier: Programming Language :: Python :: 3.10
Classifier: Programming Language :: Python :: 3.11
Requires-Dist: Pygments (>=2.10.0,<3.0.0)
Requires-Dist: jellyfish (>=1.0,<1.1)
Requires-Dist: prettytable (>=2.4.0,<3.0.0)
Requires-Dist: prompt-toolkit (>=3.0.23,<4.0.0)
Requires-Dist: pyparsing (>=3.1,<3.2)
Requires-Dist: termcolor (>=2.1.0,<2.2.0)
Requires-Dist: typing-inspect (>=0.7.1,<0.8.0)
Requires-Dist: wcwidth (>=0.2.5,<0.3.0)
